{
	"Entity": {
		"description": "Entity base class",
		"children" : {
			"id" : {
				"type" : "string",
				"description" : "text representation of the entity's ID. Does not exist for the Player entity"
			},
			"Pos": {
				"type" : "double[]",
				"description" : "describing the current X, Y and Z position of the entity.",
				"children" : {
					"0" : {
						"type" : "double",
						"description" : "x coord"
					},
					"1" : {
						"type" : "double",
						"description" : "y coord"
					},
					"2" : {
						"type" : "double",
						"description" : "z coord"
					}
				}
			},
			"Air" : {
				"type" : "int",
				"description" : "How much air the entity has, in ticks. Fills to a maximum of 300 in air, giving 15 seconds submerged before the entity starts to drown",
				"constrait" : {
					"max" : 300,
					"min" : 0
				}
			}

		}
	}
}
